{
    "data": {
        "additionalInformation": {
            "feesAndPricingUri": "https://www.bdcualliancebank.com.au/support/rates-and-fees",
            "overviewUri": "https://www.bdcualliancebank.com.au/personal-banking/savings-accounts/bonus-saver",
            "termsUri": "https://www.bdcualliancebank.com.au/personal-banking/savings-accounts/bonus-saver"
        },
        "applicationUri": "https://forms.bdcualliancebank.com.au/member-and-account-application-form?account=bonus-saver",
        "brand": "BDCU Alliance Bank",
        "brandName": "BDCU Alliance Bank",
        "description": "A savings account that rewards you with bonus interest, helping you achieve your goal sooner.",
        "effectiveFrom": "2022-09-30T14:00:00.000Z",
        "isTailored": false,
        "lastUpdated": "2022-09-30T05:43:52.623Z",
        "name": "Bonus Saver",
        "productCategory": "TRANS_AND_SAVINGS_ACCOUNTS",
        "productId": "ea815e7a-ae15-42e0-b5bc-1ae91ab4f9af",
        "fees": [
            {
                "name": "Transaction Fee - Bonus Saver",
                "amount": "3.00",
                "currency": "AUD",
                "additionalValue": "Per withdrawal",
                "feeType": "WITHDRAWAL"
            }
        ],
        "depositRates": [
            {
                "depositRateType": "VARIABLE",
                "calculationFrequency": "P1D",
                "rate": "0.0005",
                "applicationFrequency": "P1M"
            },
            {
                "rate": "0.014",
                "applicationFrequency": "P1M",
                "additionalInfo": "Bonus is applied if you make a deposit of $10 per month and make no withdrawals or debit transfers.",
                "additionalValue": "Deposit a minimum of $10 per month and make no withdrawals or balance transfer",
                "depositRateType": "BONUS",
                "calculationFrequency": "P1D"
            }
        ],
        "features": [
            {
                "featureType": "FREE_TXNS",
                "additionalInfo": "First withdrawal per month is free, then $3 per withdrawal.",
                "additionalValue": "1"
            },
            {
                "featureType": "DIGITAL_BANKING"
            },
            {
                "featureType": "OTHER",
                "additionalInfo": "Bonus Interest is paid if you make deposit of $10 each calendar month, and make no withdrawals or debit transfers.",
                "additionalValue": "Bonus Interest"
            }
        ]
    },
    "links": {
        "self": "https://api.cdr.bdcualliancebank.com.au/cds-au/v1/banking/products/ea815e7a-ae15-42e0-b5bc-1ae91ab4f9af"
    },
    "meta": {}
}