[
    {
        "rates": [
            {
                "time": 1660963668,
                "rate": 6.79
            }
        ],
        "period": 36,
        "lendingRateType": "FIXED",
        "repaymentType": "PRINCIPAL_AND_INTEREST",
        "name": "P36M FIXED PRINCIPAL_AND_INTEREST"
    },
    {
        "rates": [
            {
                "time": 1660963668,
                "rate": 5.59
            }
        ],
        "lendingRateType": "VARIABLE",
        "repaymentType": "PRINCIPAL_AND_INTEREST",
        "name": "VARIABLE PRINCIPAL_AND_INTEREST"
    }
]