{
    "links": {
        "self": "https://api.anz/cds-au/v1/banking/products/6396b1bd-1c47-9c28-59b8-6847f208a9a7"
    },
    "data": {
        "brand": "ANZ",
        "cardArt": [],
        "bundles": [],
        "effectiveFrom": "2019-06-30T14:00:00.000Z",
        "depositRates": [],
        "isTailored": false,
        "lastUpdated": "2022-12-13T03:00:00.000Z",
        "fees": [
            {
                "currency": "AUD",
                "additionalInfo": "Annual service fee for the credit card account",
                "feeType": "PERIODIC",
                "name": "Account Service",
                "discounts": [
                    {
                        "discountType": "ELIGIBILITY_ONLY",
                        "additionalInfo": "Exclusive offer for existing ANZ customers. New card. T&Cs, eligibility criteria, fees and charges apply.",
                        "eligibility": [],
                        "description": "Exclusive offer for existing ANZ customers. $0 annual service fee in the first year for new cards.",
                        "amount": "0.00"
                    }
                ],
                "additionalValue": "P1Y",
                "amount": "320.00"
            },
            {
                "currency": "AUD",
                "additionalInfo": "Annual service fee for membership of the Rewards program",
                "feeType": "PERIODIC",
                "name": "Rewards Program",
                "discounts": [
                    {
                        "discountType": "ELIGIBILITY_ONLY",
                        "additionalInfo": "Exclusive offer for existing ANZ customers. New card. T&Cs, eligibility criteria, fees and charges apply.",
                        "eligibility": [],
                        "description": "Exclusive offer for existing ANZ customers. $0 annual rewards program fee in the first year for new cards only.",
                        "amount": "0.00"
                    }
                ],
                "additionalValue": "P1Y",
                "amount": "55.00"
            },
            {
                "currency": "AUD",
                "additionalInfo": "Annual service fee for each additional cardholder",
                "feeType": "PERIODIC",
                "name": "Additional Cardholder Account Service",
                "discounts": [],
                "additionalValue": "P1Y",
                "amount": "10.00"
            },
            {
                "currency": "AUD",
                "additionalInfo": "Annual service fee for each additional cardholder's membership of the Rewards program",
                "feeType": "PERIODIC",
                "name": "Additional Cardholder Rewards Program",
                "discounts": [],
                "additionalValue": "P1Y",
                "amount": "55.00"
            },
            {
                "currency": "AUD",
                "additionalInfo": "We generally charge 3% of any cash advance from your credit card account, subject to a minimum of $4 if the cash advance is made outside Australia. The amount on which the fee is charged may include fees and other charges related to the cash advance transaction. For ANZ Rewards Travel Adventures cards, we won\u2019t charge a Cash Advance Fee on cash withdrawals made outside Australia. See your letter of offer for details (including how we calculate the fee and when it applies).",
                "feeType": "WITHDRAWAL",
                "name": "Cash Advance",
                "transactionRate": "0.03",
                "additionalValue": "P1Y",
                "discounts": []
            },
            {
                "currency": "AUD",
                "feeType": "PURCHASE",
                "name": "Overseas Transaction Fee",
                "transactionRate": "0.03",
                "additionalValue": "P1Y",
                "discounts": []
            },
            {
                "currency": "AUD",
                "feeType": "EVENT",
                "name": "Late Payment",
                "amount": "20.00",
                "additionalValue": "P1Y",
                "discounts": [
                    {
                        "discountType": "ELIGIBILITY_ONLY",
                        "additionalInfo": "This applies to all onsale consumer cards products.",
                        "additionalInfoUri": "https://www.anz.com.au/content/dam/anzcomau/documents/pdf/personal-account-fees-charges.pdf",
                        "description": "No Late Payment Fee will apply if you hold an ANZ Access Basic Account. ",
                        "eligibility": [],
                        "amount": "0.00"
                    }
                ]
            },
            {
                "currency": "AUD",
                "name": "Over Limit",
                "feeType": "EVENT",
                "additionalInfoUri": "https://www.anz.com.au/content/dam/anzcomau/documents/pdf/personal-account-fees-charges.pdf",
                "discounts": [
                    {
                        "discountType": "ELIGIBILITY_ONLY",
                        "additionalInfoUri": "https://www.anz.com.au/content/dam/anzcomau/documents/pdf/personal-account-fees-charges.pdf",
                        "description": "You will not be charged an Overlimit Fee where ANZ provides you with an Informal Overlimit amount during the Statement Period and: - you hold an ANZ Access Basic Account; or - we determine that: (1) Your account was opened before 18 June 2012 and you have asked us to decline transactions (in most cases) that will take you over the credit limit; or (2) Your account was opened on or after 18 June 2012 and at the time the Informal Overlimit amount is provided you have not consented, or you have withdrawn your consent to being charged an Overlimit Fee (unless you are charged an Overlimit Fee in accordance with paragraph A in respect of an earlier Informal Overlimit amount).",
                        "eligibility": [],
                        "amount": "0.00"
                    }
                ],
                "additionalValue": "P1Y",
                "amount": "20.00"
            }
        ],
        "productId": "6396b1bd-1c47-9c28-59b8-6847f208a9a7",
        "description": "Our highest Reward Points earning potential",
        "lendingRates": [
            {
                "lendingRateType": "PURCHASE",
                "additionalInfo": "Rates are subject to change",
                "rate": "0.2024",
                "tiers": [],
                "interestPaymentDue": "IN_ARREARS"
            },
            {
                "lendingRateType": "CASH_ADVANCE",
                "additionalInfo": "Rates are subject to change. The interest rate that applies to cash advances is currently equivalent to the interest rate that applies to standard balance transfers.",
                "rate": "0.2124",
                "tiers": [],
                "interestPaymentDue": "IN_ARREARS"
            },
            {
                "calculationFrequency": "P1D",
                "lendingRateType": "INTRODUCTORY",
                "additionalInfo": "1.99% on Promotional Balance Transfers for 6 months. Existing Customers Only. Conditions Apply.",
                "tiers": [],
                "rate": "0.0199",
                "additionalValue": "P1M",
                "interestPaymentDue": "IN_ARREARS"
            }
        ],
        "productCategory": "CRED_AND_CHRG_CARDS",
        "eligibility": [
            {
                "eligibilityType": "MIN_AGE",
                "additionalInfo": "You must be 18 years of age or older to apply",
                "additionalValue": "18"
            },
            {
                "additionalValue": "Australian Citizen, Australian Permanent Resident, New Zealand Citizen or have more than 9 months left on a valid working visa, student visa, business visa or investor visa",
                "eligibilityType": "RESIDENCY_STATUS"
            }
        ],
        "constraints": [
            {
                "additionalValue": "15000.00",
                "constraintType": "MIN_LIMIT"
            }
        ],
        "features": [
            {
                "featureType": "ADDITIONAL_CARDS",
                "additionalInfo": "Up to 9 additional cardholders for an annual fee of $65 per additional cardholder.",
                "additionalValue": "9"
            },
            {
                "additionalInfoUri": "https://www.anz.com.au/content/dam/anzcomau/documents/pdf/premium-cards-insurances.pdf?CID=af:obank:cc",
                "additionalValue": "International Travel Insurance",
                "featureType": "INSURANCE"
            },
            {
                "additionalInfoUri": "https://www.anz.com.au/content/dam/anzcomau/documents/pdf/anz-platinum-and-black-complimentary-insurance-booklet.pdf",
                "additionalValue": "Domestic Travel Insurance",
                "featureType": "INSURANCE"
            },
            {
                "additionalInfoUri": "https://www.anz.com.au/content/dam/anzcomau/documents/pdf/premium-cards-insurances.pdf?CID=af:obank:cc",
                "additionalValue": "Rental Vehicle Excess in Australia Insurance\t",
                "featureType": "INSURANCE"
            },
            {
                "additionalInfoUri": "https://www.anz.com.au/content/dam/anzcomau/documents/pdf/premium-cards-insurances.pdf?CID=af:obank:cc",
                "additionalValue": "Extended Warranty Insurance",
                "featureType": "INSURANCE"
            },
            {
                "additionalInfoUri": "https://www.anz.com.au/content/dam/anzcomau/documents/pdf/premium-cards-insurances.pdf?CID=af:obank:cc",
                "additionalValue": "Purchase Protection Insurance",
                "featureType": "INSURANCE"
            },
            {
                "additionalInfoUri": "https://www.anz.com.au/content/dam/anzcomau/documents/pdf/anz-creditcards-conditions-of-use.pdf?CID=af:obank:cc",
                "featureType": "INTEREST_FREE",
                "additionalInfo": "Up to 55 days interest free days on purchases",
                "additionalValue": "P55D"
            },
            {
                "additionalInfoUri": "https://mobilepayments.anz.com/?CID=af:obank:cc",
                "additionalValue": "Apple Pay",
                "featureType": "DIGITAL_WALLET"
            },
            {
                "additionalInfoUri": "https://mobilepayments.anz.com/?CID=af:obank:cc",
                "additionalValue": "Google Pay",
                "featureType": "DIGITAL_WALLET"
            },
            {
                "additionalInfoUri": "https://mobilepayments.anz.com/?CID=af:obank:cc",
                "additionalValue": "Samsung Pay",
                "featureType": "DIGITAL_WALLET"
            },
            {
                "additionalInfoUri": "https://mobilepayments.anz.com/?CID=af:obank:cc",
                "additionalValue": "Fitbit Pay",
                "featureType": "DIGITAL_WALLET"
            },
            {
                "additionalInfoUri": "https://mobilepayments.anz.com/?CID=af:obank:cc",
                "additionalValue": "Garmin Pay",
                "featureType": "DIGITAL_WALLET"
            },
            {
                "additionalInfoUri": "https://www.anz.com.au/ways-to-bank/internet-banking/personal/?CID=af:obank:cc",
                "additionalInfo": "Access using ANZ Internet Banking or ANZ App",
                "featureType": "DIGITAL_BANKING"
            },
            {
                "additionalInfoUri": "https://www.anz.com.au/ways-to-bank/more/bpay/?CID=af:obank:cc",
                "additionalValue": "BPAY",
                "featureType": "BILL_PAYMENT"
            },
            {
                "additionalInfoUri": "https://www.anz.com.au/content/dam/anzcomau/documents/pdf/anz-rewards-program-terms-conditions.pdf?CID=af:obank:cc",
                "featureType": "LOYALTY_PROGRAM",
                "additionalInfo": "2 Reward Points per $1 spent on eligible purchases up to and including $5,000 per statement period. 1 Reward Point per $1 spent on eligible purchases above $5,000 per statement period.",
                "additionalValue": "ANZ Rewards Points"
            },
            {
                "featureType": "BALANCE_TRANSFERS"
            },
            {
                "additionalInfoUri": "https://www.anz.com.au/personal/credit-cards/rewards/black/",
                "featureType": "BONUS_REWARDS",
                "additionalInfo": "150,000 extra ANZ Rewards Points and $150 back to your new ANZ Rewards Black credit card when you spend $3,000 on eligible purchases in the first 3 months from approval. New Rewards card. T&Cs, eligibility criteria, fees and charges apply.\n\n \n\n",
                "additionalValue": "150000"
            }
        ],
        "additionalInformation": {
            "eligibilityUri": "https://www.anz.com.au/personal/credit-cards/rewards/black/?CID=af:obank:cc#eligibility",
            "termsUri": "http://www.anz.com/auxiliary/rates-fees-terms/fees-terms-conditions/?CID=af:obank:cc",
            "feesAndPricingUri": "https://www.anz.com.au/personal/credit-cards/rewards/black/?CID=af:obank:cc#rates",
            "overviewUri": "https://www.anz.com.au/personal/credit-cards/rewards/black?CID=af:obank:cc"
        },
        "applicationUri": "https://creditcardapp.anz.com/#/?sourcecode_1=IXKR&apptype=RB&CID=af:obank:cc",
        "name": "ANZ Rewards Black"
    }
}