{
    "data": {
        "productId": "037d5d47-6053-49af-972f-2a96d56ecf19",
        "lastUpdated": "2022-02-04T06:14:35.263156Z",
        "productCategory": "PERS_LOANS",
        "name": "L16 Personal Loan (Unsecured) - $2k to $5k Home Owner",
        "description": "L16 Personal Loan (Unsecured) - $2k to $5k Home Owner",
        "brand": "FAMILY FIRST CREDIT UNION LTD",
        "brandName": "FAMILY FIRST",
        "isTailored": false,
        "additionalInformation": {},
        "lendingRates": [
            {
                "lendingRateType": "VARIABLE",
                "rate": "0.125",
                "comparisonRate": "0.2418",
                "calculationFrequency": "P1D",
                "applicationFrequency": "P1M",
                "interestPaymentDue": "IN_ARREARS",
                "additionalInfo": "Comparison Rate based on a typical Personal Loan of $2,500 repayable over 2 years"
            }
        ]
    },
    "links": {
        "self": "https://public.cdr.familyfirst.com.au/cds-au/v1/banking/products/037d5d47-6053-49af-972f-2a96d56ecf19"
    },
    "meta": {}
}