{
    "data": {
        "features": [
            {
                "featureType": "REDRAW",
                "additionalInfo": "",
                "additionalInfoUri": "https://www.cwcu.com.au/about-us/news-central/february-2020/what-is-a-redraw-facility"
            },
            {
                "featureType": "OFFSET",
                "additionalInfo": "",
                "additionalInfoUri": "https://www.cwcu.com.au/savings/other-savings-accounts"
            },
            {
                "featureType": "DIGITAL_BANKING",
                "additionalInfo": "",
                "additionalInfoUri": "https://www.cwcu.com.au/other-services/cards-and-ways-to-bank/redinet-online-banking"
            },
            {
                "featureType": "OTHER",
                "additionalInfo": "Maximum term 30 years",
                "additionalInfoUri": ""
            }
        ],
        "constraints": [
            {
                "constraintType": "MIN_BALANCE",
                "additionalValue": "10000.00",
                "additionalInfo": "",
                "additionalInfoUri": ""
            }
        ],
        "eligibility": [
            {
                "eligibilityType": "RESIDENCY_STATUS",
                "additionalValue": "Australian Resident only",
                "additionalInfo": "",
                "additionalInfoUri": ""
            },
            {
                "eligibilityType": "OTHER",
                "additionalInfo": "Maximum LVR 95% subject to Lenders Mortgage Insurance approval",
                "additionalInfoUri": ""
            },
            {
                "eligibilityType": "MIN_AGE",
                "additionalValue": "18",
                "additionalInfo": "",
                "additionalInfoUri": ""
            }
        ],
        "fees": [
            {
                "name": "MORTGAGE_SMART_HOME_LOAN_ESTABLISHMENT_FEE",
                "feeType": "UPFRONT",
                "amount": "804.40",
                "accrualFrequency": "",
                "currency": "AUD",
                "additionalInfo": "Establishment fees paid on funding",
                "additionalInfoUri": ""
            },
            {
                "name": "MORTGAGE_DISCHARGE_FEE",
                "feeType": "EXIT",
                "amount": "509.94",
                "accrualFrequency": "",
                "currency": "AUD",
                "additionalInfo": "Discharge fees are paid on discharge",
                "additionalInfoUri": ""
            }
        ],
        "lendingRates": [
            {
                "lendingRateType": "VARIABLE",
                "rate": "0.0735",
                "calculationFrequency": "P1D",
                "applicationFrequency": "P1M",
                "additionalInfo": "Secured by mortgage over Residential Property",
                "additionalInfoUri": "",
                "interestPaymentDue": "IN_ARREARS",
                "comparisonRate": "0.0741",
                "repaymentType": "PRINCIPAL_AND_INTEREST"
            }
        ],
        "productId": "Mortgage_Smart_Home_Loan",
        "effectiveFrom": "2021-03-25T00:00:00.000+11:00",
        "lastUpdated": "2023-06-29T08:55:36.000+10:00",
        "productCategory": "RESIDENTIAL_MORTGAGES",
        "name": "Mortgage Smart Home Loan",
        "description": "Whether you're a first homebuyer, or looking to expand along with your family, our friendly team will work with you to find the loan that best supports your goals.",
        "brand": "CENTRAL WEST CREDIT UNION LTD",
        "brandName": "CENTRAL WEST CREDIT UNION LTD",
        "applicationUri": "https://www.cwcu.com.au/lending/apply-for-a-loan",
        "isTailored": false,
        "additionalInformation": {
            "overviewUri": "https://www.cwcu.com.au/lending/home-loans",
            "termsUri": "https://www.cwcu.com.au/disclosure-documents/conditions-of-use",
            "eligibilityUri": "https://www.cwcu.com.au/disclosure-documents/conditions-of-use",
            "feesAndPricingUri": "1",
            "bundleUri": ""
        }
    },
    "links": {
        "self": "https://ib.cwcu.com.au/openbanking/cds-au/v1/banking/products/Mortgage_Smart_Home_Loan"
    },
    "meta": {}
}