[
    {
        "rates": [
            {
                "time": 1653090298,
                "rate": 5.55
            }
        ],
        "lendingRateType": "VARIABLE",
        "name": "VARIABLE"
    },
    {
        "rates": [
            {
                "time": 1653306587,
                "rate": 3.14
            },
            {
                "time": 1653298829,
                "rate": 3.75
            }
        ],
        "lendingRateType": "VARIABLE",
        "repaymentType": "PRINCIPAL_AND_INTEREST",
        "purpose": "OWNER_OCCUPIED",
        "name": "VARIABLE PRINCIPAL_AND_INTEREST OWNER_OCCUPIED"
    }
]