{
    "data": {
        "productId": "BTMarginLending",
        "lastUpdated": "2021-12-14T09:10:21Z",
        "productCategory": "MARGIN_LOANS",
        "name": "Margin Lending",
        "description": "As market leaders in margin lending, BT has the expertise to help you make the most of your money by using gearing to leverage your equities exposure.",
        "brand": "BT",
        "isTailored": false,
        "additionalInformation": {
            "overviewUri": "https://www.bt.com.au/personal/investments/solutions/borrow-to-invest/bt-margin-loan.html",
            "termsUri": "https://www.bt.com.au/content/dam/public/btfg-bt/documents/legacy/downloads/forms/BTML-Application-Individual.pdf",
            "eligibilityUri": "https://www.bt.com.au/content/dam/public/btfg-bt/documents/legacy/downloads/forms/BTML-Application-Individual.pdf",
            "feesAndPricingUri": "https://www.bt.com.au/personal/prices-and-performance/margin-loan-interest-rates.html"
        },
        "features": [
            {
                "featureType": "OTHER",
                "additionalInfo": "Borrow to invest: Borrow to invest over a wide universe of shares and managed funds, including mid and small cap stocks."
            },
            {
                "featureType": "OTHER",
                "additionalInfo": "Diversify your portfolio: Choose from a competitive list of acceptable securities including shares and managed funds."
            },
            {
                "featureType": "OTHER",
                "additionalInfo": "Flexible repayments, no fees: The facility is an open-ended revolving line of credit with no set principal repayment schedule. Part or full repayments can be made at any time."
            },
            {
                "featureType": "OTHER",
                "additionalInfo": "Flexible loan structure: There are no transaction limits, no minimum amounts for cash advances, loan draw-downs or repayments. Hold securities in your name or that of a third party."
            },
            {
                "featureType": "OTHER",
                "additionalInfo": "Around the clock access: View and manage your account 24/7 online."
            },
            {
                "featureType": "OTHER",
                "additionalInfo": "Choice of acceptable securities: Choose from over 2,100 shares and managed funds with LVRs between 35% ? 75%."
            },
            {
                "featureType": "OTHER",
                "additionalInfo": "Set a regular gearing plan: Establish a regular gearing plan with a minimum loan of $2,500, and a minimum monthly investment of $250 per managed fund."
            },
            {
                "featureType": "OTHER",
                "additionalInfo": "Servicing wholesale clients: A streamlined margin loan application process, for investors who satisfy the definition of a wholesale investor."
            },
            {
                "featureType": "OTHER",
                "additionalInfo": "Call options: BT Margin Lending customers can sell covered call options against shares held on their margin loan. Options accounts can be linked by obtaining the services of any of the following approved stockbrokers for options trading. "
            }
        ],
        "eligibility": [
            {
                "eligibilityType": "MIN_AGE",
                "additionalValue": "18",
                "additionalInfo": "An individual or joint individuals who are over 18 years of age."
            },
            {
                "eligibilityType": "RESIDENCY_STATUS",
                "additionalValue": "Australian Residency ",
                "additionalInfo": "Australian resident for tax purposes."
            },
            {
                "eligibilityType": "BUSINESS",
                "additionalInfo": "An Australian company or individual trustee of a family, discretionary or testamentary trust. "
            }
        ],
        "fees": [
            {
                "name": "Establishment Fee",
                "feeType": "UPFRONT",
                "amount": "0.00",
                "additionalInfo": "No establishment fees for individuals or company applicants. These fees may change, before you apply please read the PDS and other documents provided on website."
            },
            {
                "name": "Monthly account-keeping fees",
                "feeType": "PERIODIC",
                "amount": "0.00",
                "additionalValue": "P1M",
                "additionalInfo": " No monthly account-keeping fees for this product."
            },
            {
                "name": " Transaction costs",
                "feeType": "EVENT",
                "amount": "0.00",
                "additionalInfo": "No transaction costs for this product."
            }
        ],
        "lendingRates": [
            {
                "lendingRateType": "VARIABLE",
                "rate": "0.0902",
                "calculationFrequency": "P1D",
                "applicationFrequency": "P1M",
                "additionalInfo": "Standard BT Margin Loan"
            },
            {
                "lendingRateType": "FIXED",
                "rate": "0.0855",
                "additionalValue": "P3M",
                "additionalInfo": "Fixed interest is paid in advance."
            },
            {
                "lendingRateType": "FIXED",
                "rate": "0.0855",
                "additionalValue": "P6M",
                "additionalInfo": "Fixed interest is paid in advance."
            },
            {
                "lendingRateType": "FIXED",
                "rate": "0.0855",
                "additionalValue": "P9M",
                "additionalInfo": "Fixed interest is paid in advance."
            },
            {
                "lendingRateType": "FIXED",
                "rate": "0.0855",
                "additionalValue": "P12M",
                "additionalInfo": "Fixed interest is paid in advance."
            },
            {
                "lendingRateType": "FIXED",
                "rate": "0.094",
                "additionalValue": "P24M",
                "additionalInfo": "Fixed interest is paid in advance."
            },
            {
                "lendingRateType": "FIXED",
                "rate": "0.0955",
                "additionalValue": "P36M",
                "additionalInfo": "Fixed interest is paid in advance."
            },
            {
                "lendingRateType": "FIXED",
                "rate": "0.097",
                "additionalValue": "P48M",
                "additionalInfo": "Fixed interest is paid in advance."
            },
            {
                "lendingRateType": "FIXED",
                "rate": "0.0985",
                "additionalValue": "P60M",
                "additionalInfo": "Fixed interest is paid in advance."
            },
            {
                "lendingRateType": "FIXED",
                "rate": "0.0865",
                "additionalValue": "P3M",
                "additionalInfo": "Fixed interest is paid in arrears."
            },
            {
                "lendingRateType": "FIXED",
                "rate": "0.0865",
                "additionalValue": "P6M",
                "additionalInfo": "Fixed interest is paid in arrears."
            },
            {
                "lendingRateType": "FIXED",
                "rate": "0.0865",
                "additionalValue": "P9M",
                "additionalInfo": "Fixed interest is paid in arrears."
            },
            {
                "lendingRateType": "FIXED",
                "rate": "0.0865",
                "additionalValue": "P12M",
                "additionalInfo": "Fixed interest is paid in arrears."
            },
            {
                "lendingRateType": "FIXED",
                "rate": "0.095",
                "additionalValue": "P24M",
                "additionalInfo": "Fixed interest is paid in arrears."
            },
            {
                "lendingRateType": "FIXED",
                "rate": "0.0965",
                "additionalValue": "P36M",
                "additionalInfo": "Fixed interest is paid in arrears."
            },
            {
                "lendingRateType": "FIXED",
                "rate": "0.098",
                "additionalValue": "P48M",
                "additionalInfo": "Fixed interest is paid in arrears."
            },
            {
                "lendingRateType": "FIXED",
                "rate": "0.0995",
                "additionalValue": "P60M",
                "additionalInfo": "Fixed interest is paid in arrears."
            }
        ]
    },
    "links": {
        "self": "https://digital-api.westpac.com.au/cds-au/v1/banking/products/BTMarginLending"
    },
    "meta": {}
}