{
    "data": {
        "products": [
            {
                "productId": "0979061d-8020-4c70-93f0-7b2c20bb4f12",
                "lastUpdated": "2023-10-27T23:59:59+10:00",
                "productCategory": "PERS_LOANS",
                "name": "NAB Personal Loan",
                "description": "With our unsecured personal loans, you can buy a new car, travel overseas, renovate your home, consolidate your debts and more.",
                "brand": "NAB",
                "applicationUri": "https://www.nab.com.au/personal/personal-loans/personal-loans-checklist",
                "isTailored": false,
                "additionalInformation": {
                    "overviewUri": "https://www.nab.com.au/personal/personal-loans",
                    "termsUri": "https://www.nab.com.au/personal/help-and-guidance/terms-and-conditions-for-personal-products/personal-loan-agreement-general-terms",
                    "eligibilityUri": "https://www.nab.com.au/personal/personal-loans/how-to-apply",
                    "feesAndPricingUri": "https://www.nab.com.au/personal/personal-loans"
                }
            },
            {
                "productId": "65bcb7bd-e50c-4b65-b7d7-9d5abc089a5a",
                "lastUpdated": "2023-10-27T23:59:59+10:00",
                "productCategory": "RESIDENTIAL_MORTGAGES",
                "name": "NAB Tailored Home Loan",
                "description": "Pay off your home loan sooner with our feature-packed, flexible home loan.",
                "brand": "NAB",
                "isTailored": false,
                "additionalInformation": {
                    "overviewUri": "https://www.nab.com.au/personal/home-loans/nab-tailored-home-loan",
                    "termsUri": "https://www.nab.com.au/personal/home-loans/nab-tailored-home-loan",
                    "feesAndPricingUri": "https://www.nab.com.au/content/dam/nabrwd/documents/guides/banking/personal-banking-fees-and-charges-guide.pdf",
                    "bundleUri": "https://www.nab.com.au/personal/home-loans/nab-choice-package"
                }
            },
            {
                "productId": "e34c524c-6323-468f-8e20-36130e256fd5",
                "lastUpdated": "2023-10-27T23:59:59+10:00",
                "productCategory": "RESIDENTIAL_MORTGAGES",
                "name": "NAB Base Variable Rate Home Loan",
                "description": "Get into your home sooner with our simple, low-cost home loan.",
                "brand": "NAB",
                "applicationUri": "https://www.nab.com.au/personal/home-loans/nab-online-conditional-approval",
                "isTailored": false,
                "additionalInformation": {
                    "overviewUri": "https://www.nab.com.au/personal/home-loans/nab-base-variable-rate-home-loan",
                    "termsUri": "https://www.nab.com.au/personal/home-loans/nab-base-variable-rate-home-loan",
                    "eligibilityUri": "https://www.nab.com.au/content/dam/nabrwd/documents/fact-sheets/loans/nab-basic-variable-product-sheet-pdf.pdf",
                    "feesAndPricingUri": "https://www.nab.com.au/content/dam/nabrwd/documents/guides/banking/personal-banking-fees-and-charges-guide.pdf"
                }
            },
            {
                "productId": "24873cd3-7660-42b4-8e05-92b2c846a052",
                "lastUpdated": "2023-10-23T23:59:59+10:00",
                "productCategory": "TRANS_AND_SAVINGS_ACCOUNTS",
                "name": "NAB Business Interest Account",
                "description": "A specialised transaction account for select industries or business-types that want to earn interest on every dollar.",
                "brand": "NAB",
                "isTailored": false,
                "additionalInformation": {
                    "overviewUri": "https://www.nab.com.au/business/accounts/transaction-accounts/nab-business-interest-account",
                    "termsUri": "https://www.nab.com.au/business/tools/forms-and-documents/nab-business-products",
                    "feesAndPricingUri": "https://www.nab.com.au/business/tools/rates-fees-and-charges/business-banking-fees-and-charges"
                }
            },
            {
                "productId": "b15d3e39-a110-4da6-b2f6-d634bbc99b82",
                "lastUpdated": "2023-10-23T23:59:59+10:00",
                "productCategory": "TRANS_AND_SAVINGS_ACCOUNTS",
                "name": "Business Cash Maximiser",
                "description": "An online savings account earning interest on every dollar when your balance is $10,000 or more.",
                "brand": "NAB",
                "applicationUri": "https://www.nab.com.au/business/accounts/nab-business-cash-maximiser-account-checklist",
                "isTailored": false,
                "additionalInformation": {
                    "overviewUri": "https://www.nab.com.au/business/accounts/savings-and-deposit-accounts/nab-business-cash-maximiser-account",
                    "termsUri": "https://www.nab.com.au/business/tools/forms-and-documents/nab-business-products",
                    "feesAndPricingUri": "https://www.nab.com.au/business/tools/rates-fees-and-charges/business-banking-fees-and-charges#1-nab-business-cash-maximiser"
                }
            },
            {
                "productId": "76a6fbec-0d25-4a57-b1e0-b30338a5d2f3",
                "lastUpdated": "2023-10-09T00:00:01+10:00",
                "productCategory": "TERM_DEPOSITS",
                "name": "NAB Term Deposit",
                "description": "A fixed rate, fixed term investment, providing a secure return on funds, for each agreed term.",
                "brand": "NAB",
                "isTailored": false,
                "additionalInformation": {
                    "overviewUri": "https://www.nab.com.au/personal/accounts/nab-term-deposit",
                    "termsUri": "https://www.nab.com.au/personal/help-and-guidance/terms-and-conditions-for-personal-products/terms-and-conditions-for-nab-term-deposits",
                    "feesAndPricingUri": "https://www.nab.com.au/personal/interest-rates-fees-and-charges"
                }
            },
            {
                "productId": "0c2ca397-dc24-4eb0-8fb9-e098c582ebd5",
                "lastUpdated": "2023-10-04T23:59:59+10:00",
                "productCategory": "CRED_AND_CHRG_CARDS",
                "name": "NAB Low Rate Card",
                "description": "Our lowest interest rate on purchases with no frills",
                "brand": "NAB",
                "applicationUri": "https://www.nab.com.au/personal/credit-cards/low-rate/nab-low-rate-card",
                "isTailored": false,
                "additionalInformation": {
                    "overviewUri": "https://www.nab.com.au/personal/credit-cards/low-rate/nab-low-rate-card",
                    "termsUri": "https://www.nab.com.au/personal/credit-cards/low-rate/nab-low-rate-card",
                    "eligibilityUri": "https://www.nab.com.au/personal/credit-cards/low-rate/nab-low-rate-card",
                    "feesAndPricingUri": "https://www.nab.com.au/personal/help-and-guidance/personal-banking-fees-and-charges#3a"
                }
            },
            {
                "productId": "afc433d8-947a-46b5-9f51-d15d4fb8ba3b",
                "lastUpdated": "2023-09-28T23:59:59+10:00",
                "productCategory": "RESIDENTIAL_MORTGAGES",
                "name": "NAB Defence Force Home Loan",
                "description": "A principal and interest consumer home loan with a discounted rate and optional offset capability designed only for eligible current and former ADF members.",
                "brand": "NAB",
                "isTailored": false,
                "additionalInformation": {
                    "overviewUri": "https://www.nab.com.au/personal/home-loans/nab-defence-force-home-loan",
                    "termsUri": "https://www.nab.com.au/personal/home-loans/nab-defence-force-home-loan",
                    "eligibilityUri": "https://www.nab.com.au/personal/home-loans/nab-defence-force-home-loan",
                    "feesAndPricingUri": "https://www.nab.com.au/content/dam/nabrwd/documents/guides/banking/personal-banking-fees-and-charges-guide.pdf",
                    "bundleUri": "https://www.nab.com.au/personal/home-loans/nab-defence-force-home-loan/nab-defence-force-home-loan-choice-package"
                }
            },
            {
                "productId": "f50dab04-2721-4bc5-bbb6-7638759034c4",
                "lastUpdated": "2023-07-03T23:59:59+10:00",
                "productCategory": "MARGIN_LOANS",
                "name": "NAB Margin Loan",
                "description": "With great service and competitive interest rates, we can help you take advantage of investment opportunities, both domestically and internationally.",
                "brand": "NAB",
                "applicationUri": "https://www.nabmarginlending.com.au/forms-and-resources/nab-margin-loan-checklist",
                "isTailored": false,
                "additionalInformation": {
                    "overviewUri": "https://www.nabmarginlending.com.au/products/margin-loan",
                    "termsUri": "https://www.nabmarginlending.com.au/forms-and-resources/margin-loan",
                    "eligibilityUri": "https://www.nabmarginlending.com.au/forms-and-resources/margin-loan",
                    "feesAndPricingUri": "https://www.nab.com.au/personal/super-and-investments/investment-lending/nab-margin-loan"
                }
            },
            {
                "productId": "fb63c550-4efb-4f07-91c8-948e51edb409",
                "lastUpdated": "2023-06-19T00:00:01+10:00",
                "productCategory": "TERM_DEPOSITS",
                "name": "NAB Farm Management Deposit",
                "description": "Our Farm Management Deposit can help you manage risks in these tough times. We\u2019re now also offering an interest rate concession on eligible business loans to customers with a FMD.",
                "brand": "NAB",
                "isTailored": false,
                "additionalInformation": {
                    "overviewUri": "https://www.nab.com.au/business/accounts/specialised-accounts/nab-farm-management-deposit",
                    "termsUri": "https://www.nab.com.au/personal/help-and-guidance/terms-and-conditions-for-personal-products/terms-and-conditions-for-nab-term-deposits",
                    "feesAndPricingUri": "https://www.nab.com.au/personal/interest-rates-fees-and-charges"
                }
            },
            {
                "productId": "11662a88-dfad-489a-b1c0-d837ff49ea27",
                "lastUpdated": "2023-06-16T23:59:59+10:00",
                "productCategory": "TRANS_AND_SAVINGS_ACCOUNTS",
                "name": "NAB Retirement Account",
                "description": "Get more from your money in retirement and enjoy easy access to your money while earning a competitive interest rate.",
                "brand": "NAB",
                "applicationUri": "https://www.nab.com.au/personal/accounts/transaction-accounts/nab-retirement-account",
                "isTailored": false,
                "additionalInformation": {
                    "overviewUri": "https://www.nab.com.au/personal/accounts/transaction-accounts/nab-retirement-account",
                    "termsUri": "https://www.nab.com.au/personal/help-and-guidance/terms-and-conditions-for-personal-products/personal-transaction-and-savings-products",
                    "eligibilityUri": "https://www.nab.com.au/personal/accounts/transaction-accounts/nab-retirement-account",
                    "feesAndPricingUri": "https://www.nab.com.au/personal/interest-rates-fees-and-charges"
                }
            },
            {
                "productId": "11c9331a-d769-4554-bebd-75573147dff3",
                "lastUpdated": "2023-06-16T23:59:59+10:00",
                "productCategory": "TRANS_AND_SAVINGS_ACCOUNTS",
                "name": "NAB Business Everyday Account ($10 monthly fee)",
                "description": "Get greater certainty of your costs with a flat monthly fee.",
                "brand": "NAB",
                "applicationUri": "https://www.nab.com.au/business/accounts/transaction-accounts/low-fee-business-account",
                "isTailored": false,
                "additionalInformation": {
                    "overviewUri": "https://www.nab.com.au/business/accounts/transaction-accounts/low-fee-business-account",
                    "termsUri": "https://www.nab.com.au/business/tools/forms-and-documents/nab-business-products",
                    "eligibilityUri": "https://www.nab.com.au/business/accounts/transaction-accounts/low-fee-business-account",
                    "feesAndPricingUri": "https://www.nab.com.au/business/tools/rates-fees-and-charges/business-banking-fees-and-charges"
                }
            },
            {
                "productId": "137d748b-a82e-4238-96cb-f29a8e301a84",
                "lastUpdated": "2023-06-16T23:59:59+10:00",
                "productCategory": "TRANS_AND_SAVINGS_ACCOUNTS",
                "name": "NAB Farm Management Account",
                "description": "A transaction account for rural producers and farming businesses.",
                "brand": "NAB",
                "isTailored": false,
                "additionalInformation": {
                    "overviewUri": "https://www.nab.com.au/business/accounts/specialised-accounts/nab-farm-management-account",
                    "termsUri": "https://www.nab.com.au/business/tools/forms-and-documents/nab-business-products",
                    "feesAndPricingUri": "https://www.nab.com.au/business/tools/rates-fees-and-charges/business-banking-fees-and-charges"
                }
            },
            {
                "productId": "2d188a0a-4e27-4c0f-9a6c-2eccdf534f91",
                "lastUpdated": "2023-06-16T23:59:59+10:00",
                "productCategory": "TRANS_AND_SAVINGS_ACCOUNTS",
                "name": "NAB Reward Saver",
                "description": "Grow your savings faster with bonus interest for regular deposits and no withdrawals.",
                "brand": "NAB",
                "applicationUri": "https://www.nab.com.au/personal/accounts/savings-accounts/nab-reward-saver",
                "isTailored": false,
                "additionalInformation": {
                    "overviewUri": "https://www.nab.com.au/personal/accounts/savings-accounts/nab-reward-saver",
                    "termsUri": "https://www.nab.com.au/personal/help-and-guidance/terms-and-conditions-for-personal-products/personal-transaction-and-savings-products",
                    "feesAndPricingUri": "https://www.nab.com.au/personal/interest-rates-fees-and-charges"
                }
            },
            {
                "productId": "88e4d085-8981-4f5e-93d0-05609fd30efd",
                "lastUpdated": "2023-06-16T23:59:59+10:00",
                "productCategory": "OVERDRAFTS",
                "name": "NAB Business Overdraft",
                "description": "Manage peaks and troughs in your cash flow with an overdraft on your transaction account, starting from $20K.",
                "brand": "NAB",
                "applicationUri": "https://www.nab.com.au/business/loans-and-finance/business-overdrafts/nab-business-overdraft",
                "isTailored": false,
                "additionalInformation": {
                    "overviewUri": "https://www.nab.com.au/business/loans-and-finance/business-overdrafts/nab-business-overdraft",
                    "termsUri": "https://www.nab.com.au/content/dam/nabrwd/documents/terms-and-conditions/loans/nab-business-lending-general-terms.pdf",
                    "feesAndPricingUri": "https://www.nab.com.au/business/tools/rates-fees-and-charges"
                }
            },
            {
                "productId": "a97fad3e-9d44-4b4e-8279-3722edefae52",
                "lastUpdated": "2023-06-16T23:59:59+10:00",
                "productCategory": "TRANS_AND_SAVINGS_ACCOUNTS",
                "name": "NAB iSaver",
                "description": "Access your savings whenever you need them, without affecting your interest rate.",
                "brand": "NAB",
                "applicationUri": "https://www.nab.com.au/personal/accounts/savings-accounts/nab-isaver",
                "isTailored": false,
                "additionalInformation": {
                    "overviewUri": "https://www.nab.com.au/personal/accounts/savings-accounts/nab-isaver",
                    "termsUri": "https://www.nab.com.au/personal/help-and-guidance/terms-and-conditions-for-personal-products/personal-transaction-and-savings-products",
                    "feesAndPricingUri": "https://www.nab.com.au/personal/interest-rates-fees-and-charges"
                }
            },
            {
                "productId": "aac61051-cf63-4499-977a-4c20bbd0040b",
                "lastUpdated": "2023-06-16T23:59:59+10:00",
                "productCategory": "TRANS_AND_SAVINGS_ACCOUNTS",
                "name": "NAB Community Fee Saver",
                "description": "A transaction account for your not-for-profit organisation or community group.",
                "brand": "NAB",
                "isTailored": false,
                "additionalInformation": {
                    "overviewUri": "https://www.nab.com.au/business/accounts/specialised-accounts/nab-community-fee-saver",
                    "termsUri": "https://www.nab.com.au/business/tools/forms-and-documents/nab-business-products",
                    "eligibilityUri": "https://www.nab.com.au/business/accounts/specialised-accounts/nab-community-fee-saver",
                    "feesAndPricingUri": "https://www.nab.com.au/business/tools/rates-fees-and-charges/business-banking-fees-and-charges#1-how-fees-are-calculated"
                }
            },
            {
                "productId": "d6092182-50de-4d95-bcc1-358412324ee8",
                "lastUpdated": "2023-06-16T23:59:59+10:00",
                "productCategory": "TRANS_AND_SAVINGS_ACCOUNTS",
                "name": "NAB Business Everyday Account ($0 monthly fee)",
                "description": "Embrace the flexibility of only paying for what you need",
                "brand": "NAB",
                "applicationUri": "https://www.nab.com.au/business/accounts/transaction-accounts/no-monthly-fee-business-account",
                "isTailored": false,
                "additionalInformation": {
                    "overviewUri": "https://www.nab.com.au/business/accounts/transaction-accounts/no-monthly-fee-business-account",
                    "termsUri": "https://www.nab.com.au/business/tools/forms-and-documents/nab-business-products",
                    "eligibilityUri": "https://www.nab.com.au/business/accounts/transaction-accounts/no-monthly-fee-business-account",
                    "feesAndPricingUri": "https://www.nab.com.au/business/tools/rates-fees-and-charges/business-banking-fees-and-charges"
                }
            },
            {
                "productId": "9bf0e4ba-7cf3-479a-a940-54c2b736c955",
                "lastUpdated": "2023-06-07T23:59:59+10:00",
                "productCategory": "TRANS_AND_SAVINGS_ACCOUNTS",
                "name": "NAB Corporate Cheque Account",
                "description": "A transaction account for Corporate, Institutional and large business customers.",
                "brand": "NAB",
                "isTailored": true,
                "additionalInformation": {
                    "termsUri": "https://www.nab.com.au/content/dam/nabrwd/documents/terms-and-conditions/banking/nab-corporate-cheque-account-tcs.pdf"
                }
            },
            {
                "productId": "084a4d49-6285-4f9d-911d-02a728cc3337",
                "lastUpdated": "2023-06-01T23:59:59+10:00",
                "productCategory": "BUSINESS_LOANS",
                "name": "NAB Equity Builder",
                "description": "Grow your investments beyond property. Diversify and invest in financial assets with loans starting from $10K.",
                "brand": "NAB",
                "applicationUri": "https://www.nabmarginlending.com.au/forms-and-resources/nab-equity-builder-checklist",
                "isTailored": false,
                "additionalInformation": {
                    "overviewUri": "https://www.nab.com.au/personal/super-and-investments/investment-lending/nab-equity-builder",
                    "termsUri": "https://www.nabmarginlending.com.au/forms-and-resources/equity-builder",
                    "eligibilityUri": "https://www.nabmarginlending.com.au/forms-and-resources/equity-builder",
                    "feesAndPricingUri": "https://www.nabmarginlending.com.au/products/equity-builder"
                }
            },
            {
                "productId": "9d7046e7-ca0d-44ce-98d2-0ae80d9dcdd6",
                "lastUpdated": "2023-06-01T23:59:59+10:00",
                "productCategory": "MARGIN_LOANS",
                "name": "NAB Super Lever",
                "description": "A limited recourse margin loan designed specifically for Self Managed Super Funds who want to invest in shares and managed funds.",
                "brand": "NAB",
                "applicationUri": "https://www.nabmarginlending.com.au/investor/forms-and-resources/application-kit",
                "isTailored": false,
                "additionalInformation": {
                    "overviewUri": "https://www.nabmarginlending.com.au/products/smsf-super-lever",
                    "termsUri": "https://www.nabmarginlending.com.au/forms-and-resources/super-lever",
                    "eligibilityUri": "https://www.nabmarginlending.com.au/forms-and-resources/super-lever",
                    "feesAndPricingUri": "https://www.nabmarginlending.com.au/investor/products/smsf-super-lever#rates"
                }
            },
            {
                "productId": "74a3b3bc-af32-441c-b4cd-c38c8717fd56",
                "lastUpdated": "2023-05-12T23:59:59+10:00",
                "productCategory": "OVERDRAFTS",
                "name": "NAB QuickBiz Overdraft",
                "description": "An unsecured business overdraft is a line of credit that you can easily access anytime.",
                "brand": "NAB",
                "applicationUri": "https://www.nab.com.au/business/loans-and-finance/business-overdrafts/nab-quickbiz-overdraft",
                "isTailored": false,
                "additionalInformation": {
                    "overviewUri": "https://www.nab.com.au/business/loans-and-finance/business-overdrafts/nab-quickbiz-overdraft",
                    "termsUri": "https://www.nab.com.au/content/dam/nabrwd/documents/terms-and-conditions/loans/nab-business-lending-general-terms.pdf",
                    "eligibilityUri": "https://www.nab.com.au/business/loans-and-finance/business-overdrafts/nab-quickbiz-overdraft",
                    "feesAndPricingUri": "https://www.nab.com.au/business/tools/rates-fees-and-charges/business-banking-fees-and-charges"
                }
            },
            {
                "productId": "ef0c8b23-e9ae-49af-9c0f-e31b4a27f542",
                "lastUpdated": "2023-05-12T23:59:59+10:00",
                "productCategory": "BUSINESS_LOANS",
                "name": "NAB Business Options Loan",
                "description": "An easy to understand medium to long term business loan up to $1 million, ideal for growing your business.",
                "brand": "NAB",
                "isTailored": false,
                "additionalInformation": {
                    "overviewUri": "https://www.nab.com.au/business/loans-and-finance/business-loans/nab-business-options-loans",
                    "termsUri": "https://www.nab.com.au/content/dam/nabrwd/documents/terms-and-conditions/loans/nab-business-lending-general-terms.pdf",
                    "feesAndPricingUri": "https://www.nab.com.au/business/tools/rates-fees-and-charges"
                }
            },
            {
                "productId": "98d30e6f-d7f1-4308-ba76-d5407ba10875",
                "lastUpdated": "2023-04-03T23:59:59+10:00",
                "productCategory": "REGULATED_TRUST_ACCOUNTS",
                "name": "NAB Statutory Trust Account",
                "description": "A transaction account to keep your clients\u2019 money in trust and meet your industry\u2019s regulatory requirements.",
                "brand": "NAB",
                "isTailored": false,
                "additionalInformation": {
                    "overviewUri": "https://www.nab.com.au/business/accounts/specialised-accounts/nab-statutory-trust-account",
                    "termsUri": "https://www.nab.com.au/business/accounts/specialised-accounts/nab-statutory-trust-account/statutory-trust-accounts-terms-and-conditions",
                    "eligibilityUri": "https://www.nab.com.au/business/accounts/specialised-accounts/nab-statutory-trust-account",
                    "feesAndPricingUri": "https://www.nab.com.au/business/tools/rates-fees-and-charges/business-banking-fees-and-charges"
                }
            },
            {
                "productId": "2b01ecff-f783-4e88-b113-40819b5014c0",
                "lastUpdated": "2022-12-16T23:59:59+10:00",
                "productCategory": "OVERDRAFTS",
                "name": "NAB Farm Management Account Overdraft",
                "description": "An overdraft on your farm account to help you manage your seasonal cash flow.",
                "brand": "NAB",
                "isTailored": false,
                "additionalInformation": {
                    "overviewUri": "https://www.nab.com.au/business/loans-and-finance/agribusiness-loans/nab-farm-management-account-overdraft",
                    "termsUri": "https://www.nab.com.au/content/dam/nabrwd/documents/terms-and-conditions/loans/nab-business-lending-general-terms.pdf",
                    "feesAndPricingUri": "https://www.nab.com.au/business/tools/rates-fees-and-charges"
                }
            },
            {
                "productId": "79281b0d-8708-41c1-b242-d18df59d4f15",
                "lastUpdated": "2022-12-16T23:59:59+10:00",
                "productCategory": "REGULATED_TRUST_ACCOUNTS",
                "name": "Victorian Retail Lease Account",
                "description": "A transaction account to hold the security deposit paid by the Tenant to a Landlord under a lease in relation to a 'retail premises' in Victoria.",
                "brand": "NAB",
                "isTailored": false,
                "additionalInformation": {
                    "overviewUri": "https://www.nab.com.au/business/accounts/specialised-accounts/nab-statutory-trust-account/statutory-trust-accounts-terms-and-conditions",
                    "termsUri": "https://www.nab.com.au/business/accounts/specialised-accounts/nab-statutory-trust-account/statutory-trust-accounts-terms-and-conditions",
                    "eligibilityUri": "https://www.nab.com.au/business/accounts/specialised-accounts/nab-statutory-trust-account",
                    "feesAndPricingUri": "https://www.nab.com.au/business/tools/rates-fees-and-charges/business-banking-fees-and-charges"
                }
            },
            {
                "productId": "263a9294-f2d8-4f5e-885c-363e1c2010b9",
                "lastUpdated": "2022-11-30T23:59:59+10:00",
                "productCategory": "CRED_AND_CHRG_CARDS",
                "name": "NAB Qantas Rewards Premium Card",
                "description": "Earn Qantas Points and enjoy platinum services and complimentary insurances",
                "brand": "NAB",
                "applicationUri": "https://www.nab.com.au/personal/credit-cards/qantas-rewards/nab-qantas-rewards-premium-card",
                "isTailored": false,
                "additionalInformation": {
                    "overviewUri": "https://www.nab.com.au/personal/credit-cards/qantas-rewards/nab-qantas-rewards-premium-card",
                    "termsUri": "https://www.nab.com.au/personal/credit-cards/qantas-rewards/nab-qantas-rewards-premium-card",
                    "eligibilityUri": "https://www.nab.com.au/personal/credit-cards/qantas-rewards/nab-qantas-rewards-premium-card",
                    "feesAndPricingUri": "https://www.nab.com.au/personal/help-and-guidance/personal-banking-fees-and-charges#3a"
                }
            },
            {
                "productId": "3195a729-255e-45e0-b180-b059119bcb8b",
                "lastUpdated": "2022-11-30T23:59:59+10:00",
                "productCategory": "CRED_AND_CHRG_CARDS",
                "name": "NAB Low Fee Platinum Card",
                "description": "Our lowest annual fee card with platinum services and complimentary insurances",
                "brand": "NAB",
                "applicationUri": "https://www.nab.com.au/personal/banking/credit-cards/nab-low-fee-platinum-card",
                "isTailored": false,
                "additionalInformation": {
                    "overviewUri": "https://www.nab.com.au/personal/banking/credit-cards/nab-low-fee-platinum-card",
                    "termsUri": "https://www.nab.com.au/personal/banking/credit-cards/nab-low-fee-platinum-card",
                    "eligibilityUri": "https://www.nab.com.au/personal/banking/credit-cards/nab-low-fee-platinum-card",
                    "feesAndPricingUri": "https://www.nab.com.au/personal/help-and-guidance/personal-banking-fees-and-charges#3a"
                }
            },
            {
                "productId": "8a47c774-0065-4850-992c-42d73253f3eb",
                "lastUpdated": "2022-11-30T23:59:59+10:00",
                "productCategory": "CRED_AND_CHRG_CARDS",
                "name": "NAB Qantas Rewards Signature Card",
                "description": "The Qantas Rewards Signature card gives customers the opportunity to be rewarded for the purchases they make by earning Qantas Frequent Flyer points at the fastest rate.\r\nIncludes Signature benefits, including complimentary insurances.",
                "brand": "NAB",
                "applicationUri": "https://www.nab.com.au/personal/credit-cards/qantas-rewards/nab-qantas-rewards-signature-card",
                "isTailored": false,
                "additionalInformation": {
                    "overviewUri": "https://www.nab.com.au/personal/credit-cards/qantas-rewards/nab-qantas-rewards-signature-card",
                    "termsUri": "https://www.nab.com.au/personal/credit-cards/qantas-rewards/nab-qantas-rewards-signature-card",
                    "eligibilityUri": "https://www.nab.com.au/personal/credit-cards/qantas-rewards/nab-qantas-rewards-signature-card",
                    "feesAndPricingUri": "https://www.nab.com.au/personal/help-and-guidance/personal-banking-fees-and-charges#3a"
                }
            },
            {
                "productId": "c43ad795-9db1-4e1f-a7f5-845714ecedfd",
                "lastUpdated": "2022-11-30T23:59:59+10:00",
                "productCategory": "CRED_AND_CHRG_CARDS",
                "name": "NAB Rewards Platinum Card",
                "description": "Earn NAB Rewards Points and enjoy platinum services and complimentary insurances",
                "brand": "NAB",
                "applicationUri": "https://www.nab.com.au/personal/credit-cards/nab-rewards/nab-rewards-platinum-card",
                "isTailored": false,
                "additionalInformation": {
                    "overviewUri": "https://www.nab.com.au/personal/credit-cards/nab-rewards/nab-rewards-platinum-card",
                    "termsUri": "https://www.nab.com.au/personal/credit-cards/nab-rewards/nab-rewards-platinum-card",
                    "eligibilityUri": "https://www.nab.com.au/personal/credit-cards/nab-rewards/nab-rewards-platinum-card",
                    "feesAndPricingUri": "https://www.nab.com.au/personal/help-and-guidance/personal-banking-fees-and-charges#3a"
                }
            },
            {
                "productId": "e10279eb-1172-48dd-b6d2-08bed9605c5d",
                "lastUpdated": "2022-11-30T23:59:59+10:00",
                "productCategory": "CRED_AND_CHRG_CARDS",
                "name": "NAB Rewards Signature Card",
                "description": "Our highest NAB Rewards Points earn rate with platinum services and complimentary insurances",
                "brand": "NAB",
                "applicationUri": "https://www.nab.com.au/personal/credit-cards/nab-rewards/nab-rewards-signature-card",
                "isTailored": false,
                "additionalInformation": {
                    "overviewUri": "https://www.nab.com.au/personal/credit-cards/nab-rewards/nab-rewards-signature-card",
                    "termsUri": "https://www.nab.com.au/personal/credit-cards/nab-rewards/nab-rewards-signature-card",
                    "eligibilityUri": "https://www.nab.com.au/personal/credit-cards/nab-rewards/nab-rewards-signature-card",
                    "feesAndPricingUri": "https://www.nab.com.au/personal/help-and-guidance/personal-banking-fees-and-charges#3a"
                }
            },
            {
                "productId": "fbce13b1-77db-4226-9f55-9028ee31884f",
                "lastUpdated": "2022-11-30T23:59:59+10:00",
                "productCategory": "CRED_AND_CHRG_CARDS",
                "name": "NAB Low Fee Card",
                "description": "Our lowest annual fee card with no frills",
                "brand": "NAB",
                "applicationUri": "https://www.nab.com.au/personal/banking/credit-cards/nab-low-fee-card",
                "isTailored": false,
                "additionalInformation": {
                    "overviewUri": "https://www.nab.com.au/personal/credit-cards/low-fee",
                    "termsUri": "https://www.nab.com.au/personal/credit-cards/low-fee",
                    "eligibilityUri": "https://www.nab.com.au/personal/help-and-guidance/personal-banking-fees-and-charges#3a",
                    "feesAndPricingUri": "https://www.nab.com.au/personal/credit-cards/low-fee/nab-low-fee-card",
                    "bundleUri": "https://www.nab.com.au/personal/credit-cards/low-fee/nab-low-fee-card"
                }
            },
            {
                "productId": "872ab7a8-5f9f-4d1a-b79f-84d7abf69393",
                "lastUpdated": "2022-11-03T23:59:59+10:00",
                "productCategory": "TRANS_AND_SAVINGS_ACCOUNTS",
                "name": "NAB Now Pay Later",
                "description": "Your no interest, fee-free way to split the cost of your purchases into four simple repayments over six weeks.",
                "brand": "NAB",
                "applicationUri": "https://www.nab.com.au/personal/buy-now-pay-later",
                "isTailored": false,
                "additionalInformation": {
                    "overviewUri": "https://www.nab.com.au/personal/buy-now-pay-later",
                    "termsUri": "https://www.nab.com.au/personal/buy-now-pay-later/terms-conditions",
                    "eligibilityUri": "https://www.nab.com.au/personal/buy-now-pay-later",
                    "feesAndPricingUri": "https://www.nab.com.au/personal/buy-now-pay-later/terms-conditions"
                }
            },
            {
                "productId": "2e235120-2ac4-4715-b6a1-57f0a9efd50d",
                "lastUpdated": "2022-10-25T23:59:59+10:00",
                "productCategory": "BUSINESS_LOANS",
                "name": "NAB Business Vehicle & Equipment Loan",
                "description": "The easy way to purchase vehicles or equipment. Keep money in your business with no upfront deposit.\r\nIndicative online rates from 7.49%.",
                "brand": "NAB",
                "applicationUri": "https://nabquickbizloan.nab.com.au/#/equipment-loan/start",
                "isTailored": true,
                "additionalInformation": {
                    "overviewUri": "https://www.nab.com.au/business/loans-and-finance/vehicle-or-equipment/vehicle-and-equipment-loan",
                    "eligibilityUri": "https://www.nab.com.au/business/loans-and-finance/vehicle-or-equipment/vehicle-and-equipment-loan/vehicle-loan-application-process",
                    "feesAndPricingUri": "https://www.nab.com.au/business/tools/rates-fees-and-charges/business-banking-fees-and-charges"
                }
            },
            {
                "productId": "9219179c-e1cd-4de1-b0a9-12e47c16fcff",
                "lastUpdated": "2022-08-11T23:59:59+10:00",
                "productCategory": "TRANS_AND_SAVINGS_ACCOUNTS",
                "name": "NAB Queensland Project Trust Accounts",
                "description": "If you\u2019re in the building industry, NAB Project Trusts can help avoid untimely, incorrect and non-payments.",
                "brand": "NAB",
                "applicationUri": "https://www.nab.com.au/business/accounts/specialised-accounts/project-trusts",
                "isTailored": true,
                "additionalInformation": {
                    "overviewUri": "https://www.nab.com.au/business/accounts/specialised-accounts/project-trusts"
                }
            },
            {
                "productId": "afa21411-ef95-470e-9053-83d8cd33ddc6",
                "lastUpdated": "2022-07-15T23:59:59+10:00",
                "productCategory": "TRANS_AND_SAVINGS_ACCOUNTS",
                "name": "NAB Cash Manager Account",
                "description": "Manage your investment cash flows with an investment-friendly transaction account",
                "brand": "NAB",
                "applicationUri": "https://www.nab.com.au/common/forms/nab-cash-manager",
                "isTailored": false,
                "additionalInformation": {
                    "overviewUri": "https://www.nab.com.au/personal/accounts/savings-accounts/nab-cash-manager",
                    "termsUri": "https://www.nab.com.au/personal/help-and-guidance/nab-cash-manager-terms-and-conditions",
                    "eligibilityUri": "https://www.nab.com.au/personal/accounts/savings-accounts/nab-cash-manager",
                    "feesAndPricingUri": "https://www.nab.com.au/personal/interest-rates-fees-and-charges"
                }
            },
            {
                "productId": "2bd0b7d2-4a66-4e34-a7ca-566c6e24bf80",
                "lastUpdated": "2022-06-27T23:59:59+10:00",
                "productCategory": "CRED_AND_CHRG_CARDS",
                "name": "Qantas Business Signature Card",
                "description": "Get more from your business credit card purchases. Maximise your Qantas Points.",
                "brand": "NAB",
                "applicationUri": "https://www.nab.com.au/business/business-cards/nab-qantas-business-signature-card",
                "isTailored": false,
                "additionalInformation": {
                    "overviewUri": "https://www.nab.com.au/business/business-cards/nab-qantas-business-signature-card",
                    "termsUri": "https://www.nab.com.au/business/business-credit-cards/terms-conditions",
                    "eligibilityUri": "https://www.nab.com.au/business/business-cards/nab-qantas-business-signature-card",
                    "feesAndPricingUri": "https://www.nab.com.au/business/tools/rates-fees-and-charges/business-banking-fees-and-charges?own_cid=shortURL:feesandcharges#section-3"
                }
            },
            {
                "productId": "5f5dfdb4-43b1-41e6-923e-546bb801e026",
                "lastUpdated": "2022-06-27T23:59:59+10:00",
                "productCategory": "CRED_AND_CHRG_CARDS",
                "name": "NAB Business Card",
                "description": "Manage your employee's business expenses by giving them their own charge card.",
                "brand": "NAB",
                "applicationUri": "https://www.nab.com.au/business/business-cards/nab-business-card",
                "isTailored": false,
                "additionalInformation": {
                    "overviewUri": "https://www.nab.com.au/business/business-cards/nab-business-card",
                    "termsUri": "https://www.nab.com.au/business/business-credit-cards/terms-conditions",
                    "eligibilityUri": "https://www.nab.com.au/business/business-cards/nab-business-card",
                    "feesAndPricingUri": "https://www.nab.com.au/business/tools/rates-fees-and-charges#commercial"
                }
            },
            {
                "productId": "61df032f-7fd4-492c-80ee-61ba3470d0cc",
                "lastUpdated": "2022-06-27T23:59:59+10:00",
                "productCategory": "CRED_AND_CHRG_CARDS",
                "name": "NAB StraightUp Card",
                "description": "No interest, late payment fees or foreign currency fees, just a simple monthly fee.",
                "brand": "NAB",
                "applicationUri": "https://www.nab.com.au/personal/credit-cards/nab-straightup-card/application-checklist",
                "isTailored": false,
                "additionalInformation": {
                    "overviewUri": "https://www.nab.com.au/personal/credit-cards/nab-straightup-card",
                    "termsUri": "https://www.nab.com.au/personal/help-and-guidance/terms-and-conditions-for-personal-products/personal-transaction-and-savings-products",
                    "eligibilityUri": "https://www.nab.com.au/personal/credit-cards/nab-straightup-card/application-checklist",
                    "feesAndPricingUri": "https://www.nab.com.au/personal/credit-cards/nab-straightup-card"
                }
            },
            {
                "productId": "aea04112-8a33-4d90-991a-b30ad00699a8",
                "lastUpdated": "2022-06-27T23:59:59+10:00",
                "productCategory": "CRED_AND_CHRG_CARDS",
                "name": "NAB Low Rate Business Card",
                "description": "If you\u2019re a small business, our low rate business credit card can help you manage your cash flow.",
                "brand": "NAB",
                "applicationUri": "https://www.nab.com.au/business/business-cards/nab-low-rate-business-card",
                "isTailored": false,
                "additionalInformation": {
                    "overviewUri": "https://www.nab.com.au/business/business-cards/nab-low-rate-business-card",
                    "termsUri": "https://www.nab.com.au/business/business-credit-cards/terms-conditions",
                    "eligibilityUri": "https://www.nab.com.au/business/business-cards/nab-low-rate-business-card",
                    "feesAndPricingUri": "https://www.nab.com.au/business/tools/rates-fees-and-charges/business-banking-fees-and-charges?own_cid=shortURL:feesandcharges#section-3"
                }
            },
            {
                "productId": "f5fe3ee4-b6c0-4419-975f-8ce5469f2ba3",
                "lastUpdated": "2022-06-27T23:59:59+10:00",
                "productCategory": "TRANS_AND_SAVINGS_ACCOUNTS",
                "name": "NAB Classic Banking Account",
                "description": "Meet your everyday bank account. Easy access to your money with no monthly account fees.",
                "brand": "NAB",
                "applicationUri": "https://www.nab.com.au/common/forms/account-card-application#?products=nab-classic-banking-account&own_cid=18152-1",
                "isTailored": false,
                "additionalInformation": {
                    "overviewUri": "https://www.nab.com.au/personal/accounts/transaction-accounts/nab-classic-banking",
                    "termsUri": "https://www.nab.com.au/personal/help-and-guidance/terms-and-conditions-for-personal-products/personal-transaction-and-savings-products",
                    "eligibilityUri": "https://www.nab.com.au/personal/help-and-guidance/terms-and-conditions-for-personal-products/personal-transaction-and-savings-products#parta4",
                    "feesAndPricingUri": "https://www.nab.com.au/personal/help-and-guidance/terms-and-conditions-for-personal-products/personal-transaction-and-savings-products#parta12"
                }
            },
            {
                "productId": "ff87d1af-392d-421a-903e-20b9517ea13e",
                "lastUpdated": "2022-06-27T23:59:59+10:00",
                "productCategory": "CRED_AND_CHRG_CARDS",
                "name": "NAB Rewards Business Signature Card",
                "description": "With a business credit card, earn and redeem NAB Rewards Points.",
                "brand": "NAB",
                "applicationUri": "https://www.nab.com.au/business/business-cards/nab-rewards-business-signature-card",
                "isTailored": false,
                "additionalInformation": {
                    "overviewUri": "https://www.nab.com.au/business/business-cards/nab-rewards-business-signature-card",
                    "termsUri": "https://www.nab.com.au/business/business-credit-cards/terms-conditions",
                    "eligibilityUri": "https://www.nab.com.au/business/business-cards/nab-rewards-business-signature-card",
                    "feesAndPricingUri": "https://www.nab.com.au/business/tools/rates-fees-and-charges/business-banking-fees-and-charges?own_cid=shortURL:feesandcharges#section-3"
                }
            },
            {
                "productId": "965a7f64-167c-4b26-b8ab-06e90cdb3ff4",
                "lastUpdated": "2022-06-24T23:59:59+10:00",
                "productCategory": "BUSINESS_LOANS",
                "name": "NAB QuickBiz Loan",
                "description": "Fast, unsecured business lending made easy, giving you access to funds to grow, run and invest in your business.",
                "brand": "NAB",
                "applicationUri": "https://nabquickbizloan.nab.com.au/#/start",
                "isTailored": false,
                "additionalInformation": {
                    "overviewUri": "https://www.nab.com.au/business/loans-and-finance/business-loans/nab-quickbiz-loan",
                    "termsUri": "https://www.nab.com.au/content/dam/nabrwd/documents/terms-and-conditions/loans/nab-business-lending-general-terms.pdf",
                    "eligibilityUri": "https://www.nab.com.au/business/loans-and-finance/business-loans/nab-quickbiz-loan",
                    "feesAndPricingUri": "https://www.nab.com.au/business/tools/rates-fees-and-charges/business-banking-fees-and-charges"
                }
            },
            {
                "productId": "9684c63c-223f-4166-ae1f-6d0f0018cbae",
                "lastUpdated": "2021-09-01T23:59:59+10:00",
                "productCategory": "TRANS_AND_SAVINGS_ACCOUNTS",
                "name": "NAB Professional Funds Account",
                "description": "An 'at call', interest bearing deposit account for investors with at least $500,000 to invest.",
                "brand": "NAB",
                "isTailored": true,
                "additionalInformation": {
                    "termsUri": "https://www.nab.com.au/content/dam/nabrwd/documents/terms-and-conditions/banking/nab-professional-funds-account-tcs.pdf"
                }
            },
            {
                "productId": "42fc1fb9-ebc5-49cf-abc4-2264307d9aa0",
                "lastUpdated": "2021-04-26T23:59:59+10:00",
                "productCategory": "LEASES",
                "name": "NAB Novated Lease",
                "description": "Choose the vehicle you want with salary packaging, providing a range of benefits for businesses and employees.",
                "brand": "NAB",
                "isTailored": true,
                "additionalInformation": {
                    "overviewUri": "https://www.nab.com.au/business/loans-and-finance/vehicle-or-equipment/novated-lease",
                    "eligibilityUri": "https://www.nab.com.au/business/loans-and-finance/vehicle-or-equipment/novated-lease",
                    "feesAndPricingUri": "https://www.nab.com.au/business/tools/rates-fees-and-charges/business-banking-fees-and-charges"
                }
            },
            {
                "productId": "bb2fb3c7-05da-4fc3-b2e7-71794b8abad7",
                "lastUpdated": "2021-04-26T23:59:59+10:00",
                "productCategory": "LEASES",
                "name": "NAB Finance Lease",
                "description": "Rent the vehicle or equipment your business needs and return it at the end of the lease.",
                "brand": "NAB",
                "isTailored": true,
                "additionalInformation": {
                    "overviewUri": "https://www.nab.com.au/business/loans-and-finance/vehicle-or-equipment/finance-lease",
                    "eligibilityUri": "https://www.nab.com.au/business/loans-and-finance/vehicle-or-equipment/finance-lease",
                    "feesAndPricingUri": "https://www.nab.com.au/business/tools/rates-fees-and-charges/business-banking-fees-and-charges"
                }
            },
            {
                "productId": "38962244-0d64-4d89-8bd7-59fbd01034c7",
                "lastUpdated": "2021-02-04T23:59:59+10:00",
                "productCategory": "LEASES",
                "name": "NAB Hire Purchase",
                "description": "Hire the vehicle or equipment your business needs with no upfront deposit and own it at the end of the hire period.",
                "brand": "NAB",
                "isTailored": true,
                "additionalInformation": {
                    "overviewUri": "https://www.nab.com.au/business/loans-and-finance/vehicle-or-equipment/hire-purchase",
                    "eligibilityUri": "https://www.nab.com.au/business/loans-and-finance/vehicle-or-equipment/hire-purchase",
                    "feesAndPricingUri": "https://www.nab.com.au/business/tools/rates-fees-and-charges/business-banking-fees-and-charges"
                }
            },
            {
                "productId": "acda8309-dab7-463b-a5a6-2ce58c20b47b",
                "lastUpdated": "2021-02-04T23:59:59+10:00",
                "productCategory": "TRANS_AND_SAVINGS_ACCOUNTS",
                "name": "NAB Foreign Currency Account",
                "description": "A transaction account designed for customers who frequently make or receive payments in a foreign currency.",
                "brand": "NAB",
                "applicationUri": "https://www.nab.com.au/common/forms/business/nab-foreign-currency-account#?products=nab-foreign-currency-account",
                "isTailored": false,
                "additionalInformation": {
                    "overviewUri": "https://www.nab.com.au/foreigncurrencyaccount",
                    "termsUri": "https://www.nab.com.au/business/tools/forms-and-documents/nab-foreign-currency-account-onshore",
                    "eligibilityUri": "https://www.nab.com.au/foreigncurrencyaccount",
                    "feesAndPricingUri": "https://www.nab.com.au/business/tools/rates-fees-and-charges/business-banking-fees-and-charges"
                }
            }
        ]
    }
}