[
    {
        "rates": [
            {
                "time": 1668734008,
                "rate": 6.84
            },
            {
                "time": 1657161295,
                "rate": 6.59
            },
            {
                "time": 1654137669,
                "rate": 5.39
            },
            {
                "time": 1653298829,
                "rate": 4.99
            }
        ],
        "period": "{ \"Term\": 5, \"Period\": \"Year(s)\" }",
        "lendingRateType": "FIXED",
        "name": "{ \"Term\": 5, \"Period\": \"Year(s)\" } FIXED"
    }
]